README.md
setup.py
oddrn/__init__.py
oddrn/clouds.py
oddrn/mixins.py
oddrn/oddrn.py
oddrn.egg-info/PKG-INFO
oddrn.egg-info/SOURCES.txt
oddrn.egg-info/dependency_links.txt
oddrn.egg-info/top_level.txt